mozichem_mcp/__init__.py
mozichem_mcp/mcp/__init__.py
mozichem_mcp/mcp/eos_models.py
mozichem_mcp/mcp/flash_calculation.py
mozichem_mcp_fastmcp-0.1.1.dist-info/METADATA
mozichem_mcp_fastmcp-0.1.1.dist-info/WHEEL
mozichem_mcp_fastmcp-0.1.1.dist-info/entry_points.txt
mozichem_mcp_fastmcp-0.1.1.dist-info/licenses/LICENSE
mozichem_mcp_fastmcp-0.1.1.dist-info/RECORD
