Metadata-Version: 2.4
Name: mozichem-mcp-fastmcp
Version: 0.1.1
Summary: MoziChem-MCP tools built on top of the MoziChem framework
Project-URL: Homepage, https://github.com/fastmcp-me/mozichem-mcp#readme
Project-URL: Repository, https://github.com/fastmcp-me/mozichem-mcp.git
Project-URL: Issues, https://github.com/fastmcp-me/mozichem-mcp/issues
Author-email: Sina Gilassi <sina.gilassi@gmail.com>
License-Expression: MIT
License-File: LICENSE
Classifier: Operating System :: OS Independent
Classifier: Programming Language :: Python :: 3.11
Requires-Python: >=3.11
Requires-Dist: mozichem-hub>=0.1.2
Provides-Extra: dev
Requires-Dist: black; extra == 'dev'
Requires-Dist: pytest; extra == 'dev'
Requires-Dist: ruff; extra == 'dev'
